shooki
