Metadata-Version: 1.2
Name: shooki
Version: 0.0.4
Summary: html in python
Home-page: https://github.com/shooki/shooki
Author: Gilad Kutiel
Author-email: gilad.kutiel@gmail.com
License: UNKNOWN
Platform: UNKNOWN
Requires-Python: >=3.6
